calendar_cleanup/__init__.py
calendar_cleanup/cli.py
calendar_cleanup/filter.py
calendar_cleanup/io/auth.py
calendar_cleanup/io/delete.py
calendar_cleanup/io/load.py
calendar_cleanup/schema.py
calendar_cleanup-0.3.1.dist-info/LICENSE
calendar_cleanup-0.3.1.dist-info/METADATA
calendar_cleanup-0.3.1.dist-info/WHEEL
calendar_cleanup-0.3.1.dist-info/entry_points.txt
calendar_cleanup-0.3.1.dist-info/RECORD
