Metadata-Version: 2.1
Name: calendar-cleanup
Version: 0.3.1
Summary: CLI utility to unclutter old calendar entries from WebDAV calendars.
Home-page: https://github.com/top-on/calendar-cleanup
Author: top-on
Author-email: top-on@posteo.de
Requires-Python: >=3.11,<4.0
Classifier: Programming Language :: Python :: 3
Classifier: Programming Language :: Python :: 3.11
Classifier: Programming Language :: Python :: 3.12
Requires-Dist: ical (>=6.1.0,<7.0.0)
Requires-Dist: pydantic (>=2.5.2,<3.0.0)
Requires-Dist: typer (>=0.9.0,<0.10.0)
Requires-Dist: webdav4 (>=0.9.8,<0.10.0)
